arch_mcp/__init__.py
arch_mcp/db.py
arch_mcp/rules.py
arch_mcp/server.py
arch_mcp/structures.py
arch_mcp/tools.py
arch_mcp-0.1.0.dist-info/METADATA
arch_mcp-0.1.0.dist-info/WHEEL
arch_mcp-0.1.0.dist-info/entry_points.txt
arch_mcp-0.1.0.dist-info/RECORD
