Metadata-Version: 2.4
Name: arch-mcp
Version: 0.1.0
Summary: MCP server for Python API architecture controls
Requires-Python: >=3.11
Requires-Dist: fastmcp>=3.0.0b1
Requires-Dist: psycopg[binary]>=3.1
Requires-Dist: redis>=5.0
Provides-Extra: dev
Requires-Dist: pytest-asyncio>=0.23; extra == 'dev'
Requires-Dist: pytest>=8.0; extra == 'dev'
Requires-Dist: ruff>=0.8.0; extra == 'dev'
